gym_tetris/__init__.py
gym_tetris/_registration.py
gym_tetris/actions.py
gym_tetris/tetris_env.py
gym_tetris/_app/__init__.py
gym_tetris/_app/cli.py
gym_tetris/_roms/Tetris.nes
gym_tetris-3.0.4.dist-info/LICENSE
gym_tetris-3.0.4.dist-info/METADATA
gym_tetris-3.0.4.dist-info/WHEEL
gym_tetris-3.0.4.dist-info/entry_points.txt
gym_tetris-3.0.4.dist-info/top_level.txt
gym_tetris-3.0.4.dist-info/RECORD
