Metadata-Version: 2.1
Name: gym-tetris
Version: 3.0.4
Summary: Tetris (NES) for OpenAI Gym
Home-page: https://github.com/Kautenja/gym-tetris
Author: Christian Kauten
Author-email: kautencreations@gmail.com
License: Proprietary
Keywords: OpenAI-Gym NES Tetris Reinforcement-Learning-Environment
Classifier: License :: Free For Educational Use
Classifier: Development Status :: 5 - Production/Stable
Classifier: Intended Audience :: Developers
Classifier: Intended Audience :: Science/Research
Classifier: Operating System :: MacOS :: MacOS X
Classifier: Operating System :: POSIX :: Linux
Classifier: Operating System :: Microsoft :: Windows
Classifier: Programming Language :: Python :: 3 :: Only
Classifier: Programming Language :: Python :: 3.5
Classifier: Programming Language :: Python :: 3.6
Classifier: Programming Language :: Python :: 3.7
Classifier: Programming Language :: Python :: 3.8
Classifier: Topic :: Games/Entertainment :: Side-Scrolling/Arcade Games
Classifier: Topic :: Scientific/Engineering :: Artificial Intelligence
License-File: LICENSE
Requires-Dist: nes-py (>=8.1.4)
